trytond/modules/stock_package_rate_ups/__init__.py
trytond/modules/stock_package_rate_ups/carrier.py
trytond/modules/stock_package_rate_ups/carrier.xml
trytond/modules/stock_package_rate_ups/exceptions.py
trytond/modules/stock_package_rate_ups/message.xml
trytond/modules/stock_package_rate_ups/stock.py
trytond/modules/stock_package_rate_ups/stock.xml
trytond/modules/stock_package_rate_ups/stock_inherit_wizard.py
trytond/modules/stock_package_rate_ups/tryton.cfg
trytond/modules/stock_package_rate_ups/locale/de.po
trytond/modules/stock_package_rate_ups/tests/__init__.py
trytond/modules/stock_package_rate_ups/tests/test_module.py
trytond/modules/stock_package_rate_ups/view/carrier_form.xml
m9s_stock_package_rate_ups-7.0.0.dist-info/LICENSE
m9s_stock_package_rate_ups-7.0.0.dist-info/METADATA
m9s_stock_package_rate_ups-7.0.0.dist-info/WHEEL
m9s_stock_package_rate_ups-7.0.0.dist-info/entry_points.txt
m9s_stock_package_rate_ups-7.0.0.dist-info/top_level.txt
m9s_stock_package_rate_ups-7.0.0.dist-info/RECORD
